jimmy/__init__.py
jimmy/convert.py
jimmy/io.py
jimmy/utils.py
jimmy/layers/__init__.py
jimmy/layers/attention.py
jimmy/layers/blocks.py
jimmy/layers/builders.py
jimmy/layers/configs.py
jimmy/layers/dropout.py
jimmy/layers/fastervit.py
jimmy/layers/generic.py
jimmy/layers/mamba.py
jimmy/layers/misc.py
jimmy/layers/mlp.py
jimmy/layers/norm.py
jimmy/layers/patch.py
jimmy/layers/posemb.py
jimmy/layers/sharing.py
jimmy/layers/swiglu.py
jimmy/models/__init__.py
jimmy/models/configs.py
jimmy/models/emamodel.py
jimmy/models/fastervit.py
jimmy/models/loader.py
jimmy/models/mamba.py
jimmy/models/mlla.py
jimmy/models/vit.py
jimmy/ops/__init__.py
jimmy/ops/scan.py
jimmy_vision-0.0.7.dist-info/METADATA
jimmy_vision-0.0.7.dist-info/WHEEL
jimmy_vision-0.0.7.dist-info/licenses/LICENSE.md
jimmy_vision-0.0.7.dist-info/RECORD
