Metadata-Version: 2.3
Name: jimmy-vision
Version: 0.0.7
Summary: Implementations of popular vision models in Jax (Flax NNX)
License-Expression: MIT
License-File: LICENSE.md
Requires-Python: >=3.11
Requires-Dist: einops>=0.8.0
Requires-Dist: flax>=0.8.5
Requires-Dist: jax>=0.4.27
Requires-Dist: py7zr>=0.21.1
Requires-Dist: urllib3>=2.0.0
Provides-Extra: cuda12
Requires-Dist: jax-cuda12-plugin[with-cuda]>=0.4.27; extra == 'cuda12'
Requires-Dist: jaxlib>=0.4.27; extra == 'cuda12'
Provides-Extra: torch
Requires-Dist: torch==2.4.0; extra == 'torch'
Requires-Dist: torchvision==0.19.0; extra == 'torch'
